com/lqq/tool/report/__init__.py
com/lqq/tool/report/tool_build_report.py
lqq_tool_weekreport-1.0.2.dist-info/METADATA
lqq_tool_weekreport-1.0.2.dist-info/WHEEL
lqq_tool_weekreport-1.0.2.dist-info/top_level.txt
lqq_tool_weekreport-1.0.2.dist-info/RECORD
