Metadata-Version: 2.1
Name: lqq-tool-weekreport
Version: 1.0.2
Summary: 周报自动生成工具
Home-page: https://gitee.com/linqingf/py_tool_weekreport
Author: lqq
Author-email: linqingf@sina.com
Requires-Dist: pandas
Requires-Dist: openpyxl
Requires-Dist: vika
Requires-Dist: pickle
